img2info/__init__.py
img2info/auth.py
img2info/client.py
img2info/errors.py
img2info/models.py
img2info/utils.py
img2_info-0.2.3.dist-info/METADATA
img2_info-0.2.3.dist-info/WHEEL
img2_info-0.2.3.dist-info/top_level.txt
img2_info-0.2.3.dist-info/RECORD
