Metadata-Version: 2.4
Name: img2-info
Version: 0.2.3
Summary: Im2  Python SDK (Upgraded): Clean client with auth, error handling, supports file/url/bytes/base64, includes examples and CLI, easy installation.
Author: Nguyen Truong Dat
Author-email: datgsk1 <datgsk1@gmail.com>
Requires-Python: >=3.8
Requires-Dist: requests>=2.28
